{
  "level": 13,
  "title": "옷 & 외모",
  "titleJa": "服と外見",
  "description": "일본어로 옷과 외모에 관한 표현을 배워봅시다.",
  "conversations": [
    {
      "speaker": "A",
      "variants": [
        { "japanese": "田中さん、今日の服、とても似合っていますね。", "reading": "다나카상, 쿄우노 후쿠, 토테모 니앗테이마스네.", "korean": "다나카 씨, 오늘 옷 정말 잘 어울리네요." },
        { "japanese": "その新しいコート、素敵ですね。どこで買いましたか？", "reading": "소노 아타라시이 코오토, 스테키데스네. 도코데 카이마시타카?", "korean": "그 새 코트 멋지네요. 어디서 샀어요?" },
        { "japanese": "今日は何を着ていこうか迷っています。", "reading": "쿄우와 나니오 키테이코우카 마요테이마스.", "korean": "오늘 뭘 입고 갈지 고민하고 있어요." }
      ]
    },
    {
      "speaker": "B",
      "variants": [
        { "japanese": "ありがとうございます。新しいワンピースを買ったんです。", "reading": "아리가또우고자이마스. 아타라시이 완피이스오 캇탄데스.", "korean": "감사합니다. 새 원피스를 샀어요." },
        { "japanese": "ありがとう。銀座のデパートで買いました。セールだったんです。", "reading": "아리가또우. 긴자노 데파아토데 카이마시타. 세에루닷탄데스.", "korean": "고마워요. 긴자 백화점에서 샀어요. 세일이었거든요." },
        { "japanese": "どこに行くんですか？場所によって変わりますよね。", "reading": "도코니 이쿤데스카? 바쇼니 요테 카와리마스요네.", "korean": "어디에 가는 건가요? 장소에 따라 달라지죠." }
      ]
    },
    {
      "speaker": "A",
      "variants": [
        { "japanese": "色がとてもきれいですね。その青い色が好きです。", "reading": "이로가 토테모 키레이데스네. 소노 아오이 이로가 스키데스.", "korean": "색이 정말 예쁘네요. 그 파란색이 좋아요." },
        { "japanese": "いいですね。私もそのブランドが好きです。", "reading": "이이데스네. 와타시모 소노 부란도가 스키데스.", "korean": "좋네요. 저도 그 브랜드를 좋아해요." },
        { "japanese": "友達の結婚式に行くんです。フォーマルな服が必要です。", "reading": "토모다치노 켓콩시키니 이쿤데스. 포오마루나 후쿠가 히츠요우데스.", "korean": "친구 결혼식에 가요. 정장이 필요합니다." }
      ]
    },
    {
      "speaker": "B",
      "variants": [
        { "japanese": "ありがとうございます。ヨンミンさんのジャケットもかっこいいですよ。", "reading": "아리가또우고자이마스. 용민상노 쟈켓토모 칵코이이데스요.", "korean": "감사합니다. 영민 씨의 재킷도 멋있어요." },
        { "japanese": "最近、日本ではシンプルなスタイルが流行っていますよ。", "reading": "사이킨, 니홍데와 신푸루나 스타이루가 하얏테이마스요.", "korean": "요즘 일본에서는 심플한 스타일이 유행하고 있어요." },
        { "japanese": "それなら、紺色のスーツがいいと思います。ネクタイも忘れずに。", "reading": "소레나라, 콘이로노 스우츠가 이이토 오모이마스. 네쿠타이모 와스레즈니.", "korean": "그렇다면 남색 정장이 좋을 거예요. 넥타이도 잊지 마세요." }
      ]
    },
    {
      "speaker": "A",
      "variants": [
        { "japanese": "このジャケットは韓国で買いました。韓国のファッションも人気がありますよ。", "reading": "코노 쟈켓토와 캉코쿠데 카이마시타. 캉코쿠노 팟숀모 닌키가 아리마스요.", "korean": "이 재킷은 한국에서 샀어요. 한국 패션도 인기가 있어요." },
        { "japanese": "なるほど。靴は何色がいいですか？", "reading": "나루호도. 쿠츠와 나니이로가 이이데스카?", "korean": "그렇군요. 신발은 무슨 색이 좋을까요?" },
        { "japanese": "ネクタイの結び方が苦手なんです。手伝ってもらえますか？", "reading": "네쿠타이노 무스비카타가 니가테난데스. 테츠닷테모라에마스카?", "korean": "넥타이 매는 법을 잘 못해요. 도와주실 수 있나요?" }
      ]
    },
    {
      "speaker": "B",
      "variants": [
        { "japanese": "そうですよね。K-POPの影響で韓国ファッションが日本でも人気です。", "reading": "소우데스요네. 케이팝노 에이쿄우데 캉코쿠팟숀가 니홍데모 닌키데스.", "korean": "그렇죠. K-POP 영향으로 한국 패션이 일본에서도 인기예요." },
        { "japanese": "黒い革靴がいいですよ。ベルトと合わせるといいです。", "reading": "쿠로이 카와구츠가 이이데스요. 베루토토 아와세루토 이이데스.", "korean": "검은 가죽 구두가 좋아요. 벨트와 맞추면 좋아요." },
        { "japanese": "もちろんです。こうやって結ぶんですよ。簡単でしょう？", "reading": "모치론데스. 코우얏테 무스분데스요. 칸탄데쇼우?", "korean": "물론이죠. 이렇게 매는 거예요. 간단하죠?" }
      ]
    },
    {
      "speaker": "A",
      "variants": [
        { "japanese": "確かに。今度一緒に原宿に買い物に行きましょう。", "reading": "타시카니. 콘도 잇쇼니 하라쥬쿠니 카이모노니 이키마쇼우.", "korean": "확실히요. 다음에 같이 하라주쿠에 쇼핑하러 가요." },
        { "japanese": "ありがとうございます。これで安心して出かけられます。", "reading": "아리가또우고자이마스. 코레데 안신시테 데카케라레마스.", "korean": "감사합니다. 이제 안심하고 외출할 수 있어요." },
        { "japanese": "ありがとうございます！上手にできました。助かりました。", "reading": "아리가또우고자이마스! 조우즈니 데키마시타. 타스카리마시타.", "korean": "감사합니다! 잘 되었어요. 도움이 되었습니다." }
      ]
    }
  ],
  "vocabulary": [
    { "japanese": "服", "reading": "후쿠", "korean": "옷" },
    { "japanese": "靴", "reading": "쿠츠", "korean": "신발" },
    { "japanese": "似合う", "reading": "니아우", "korean": "어울리다" },
    { "japanese": "スーツ", "reading": "스우츠", "korean": "정장" },
    { "japanese": "ネクタイ", "reading": "네쿠타이", "korean": "넥타이" },
    { "japanese": "かっこいい", "reading": "칵코이이", "korean": "멋있다" },
    { "japanese": "きれい", "reading": "키레이", "korean": "예쁘다, 깨끗하다" },
    { "japanese": "流行", "reading": "류우코우", "korean": "유행" }
  ]
}
