{
  "level": 4,
  "title": "식당에서 주문",
  "titleJa": "レストランで注文",
  "description": "일본어로 식당에서 주문하는 표현을 배워봅시다.",
  "conversations": [
    {
      "speaker": "A",
      "variants": [
        { "japanese": "すみません、メニューをお願いします。", "reading": "스미마셍, 메뉴우오 오네가이시마스.", "korean": "실례합니다, 메뉴를 부탁합니다." },
        { "japanese": "すみません、注文してもいいですか？", "reading": "스미마셍, 츄우몽시테모 이이데스카?", "korean": "실례합니다, 주문해도 될까요?" },
        { "japanese": "すみません、二人ですが、席はありますか？", "reading": "스미마셍, 후타리데스가, 세키와 아리마스카?", "korean": "실례합니다, 두 명인데 자리 있나요?" }
      ]
    },
    {
      "speaker": "B",
      "variants": [
        { "japanese": "はい、どうぞ。こちらがメニューです。", "reading": "하이, 도우조. 코치라가 메뉴우데스.", "korean": "네, 여기요. 이것이 메뉴입니다." },
        { "japanese": "はい、ご注文をどうぞ。", "reading": "하이, 고츄우몽오 도우조.", "korean": "네, 주문하세요." },
        { "japanese": "はい、こちらの席へどうぞ。", "reading": "하이, 코치라노 세키에 도우조.", "korean": "네, 이쪽 자리로 오세요." }
      ]
    },
    {
      "speaker": "A",
      "variants": [
        { "japanese": "おすすめは何ですか？", "reading": "오스스메와 난데스카?", "korean": "추천 메뉴는 뭔가요?" },
        { "japanese": "一番人気のメニューは何ですか？", "reading": "이치방닌키노 메뉴우와 난데스카?", "korean": "가장 인기 있는 메뉴는 뭔가요?" },
        { "japanese": "この店の名物料理は何ですか？", "reading": "코노 미세노 메이부츠료우리와 난데스카?", "korean": "이 가게의 대표 요리는 뭔가요?" }
      ]
    },
    {
      "speaker": "B",
      "variants": [
        { "japanese": "ラーメンがおすすめです。とても人気がありますよ。", "reading": "라아멩가 오스스메데스. 토테모 닌키가 아리마스요.", "korean": "라멘을 추천합니다. 매우 인기가 있어요." },
        { "japanese": "天ぷら定食がおすすめです。", "reading": "텐푸라테이쇼쿠가 오스스메데스.", "korean": "덴푸라 정식을 추천합니다." },
        { "japanese": "焼き魚定食が一番人気です。", "reading": "야키자카나테이쇼쿠가 이치방닌키데스.", "korean": "생선구이 정식이 가장 인기입니다." }
      ]
    },
    {
      "speaker": "A",
      "variants": [
        { "japanese": "では、ラーメンを一つお願いします。", "reading": "데와, 라아멩오 히토츠 오네가이시마스.", "korean": "그럼, 라멘 하나 부탁합니다." },
        { "japanese": "天ぷら定食を一つと、ビールを一杯ください。", "reading": "텐푸라테이쇼쿠오 히토츠토, 비이루오 잇파이 쿠다사이.", "korean": "덴푸라 정식 하나와 맥주 한 잔 주세요." },
        { "japanese": "焼き魚定食とお味噌汁をお願いします。", "reading": "야키자카나테이쇼쿠토 오미소시루오 오네가이시마스.", "korean": "생선구이 정식과 된장국을 부탁합니다." }
      ]
    },
    {
      "speaker": "B",
      "variants": [
        { "japanese": "かしこまりました。少々お待ちください。", "reading": "카시코마리마시타. 쇼우쇼우 오마치쿠다사이.", "korean": "알겠습니다. 잠시만 기다려주세요." },
        { "japanese": "はい、ラーメン一つですね。すぐお持ちします。", "reading": "하이, 라아멩 히토츠데스네. 스구 오모치시마스.", "korean": "네, 라멘 하나요. 바로 가져다 드리겠습니다." },
        { "japanese": "ご注文、確認しました。お飲み物はいかがですか？", "reading": "고츄우몽, 카쿠닌시마시타. 오노미모노와 이카가데스카?", "korean": "주문 확인했습니다. 음료는 어떠세요?" }
      ]
    },
    {
      "speaker": "A",
      "variants": [
        { "japanese": "お会計をお願いします。とても美味しかったです。", "reading": "오카이케이오 오네가이시마스. 토테모 오이시캇타데스.", "korean": "계산을 부탁합니다. 매우 맛있었습니다." },
        { "japanese": "ごちそうさまでした。お会計はいくらですか？", "reading": "고치소우사마데시타. 오카이케이와 이쿠라데스카?", "korean": "잘 먹었습니다. 계산은 얼마인가요?" },
        { "japanese": "美味しかったです。カードで払えますか？", "reading": "오이시캇타데스. 카아도데 하라에마스카?", "korean": "맛있었습니다. 카드로 결제할 수 있나요?" }
      ]
    }
  ],
  "vocabulary": [
    { "japanese": "メニュー", "reading": "메뉴우", "korean": "메뉴" },
    { "japanese": "注文", "reading": "츄우몽", "korean": "주문" },
    { "japanese": "おすすめ", "reading": "오스스메", "korean": "추천" },
    { "japanese": "美味しい", "reading": "오이시이", "korean": "맛있다" },
    { "japanese": "お会計", "reading": "오카이케이", "korean": "계산" },
    { "japanese": "定食", "reading": "테이쇼쿠", "korean": "정식" },
    { "japanese": "飲み物", "reading": "노미모노", "korean": "음료" }
  ]
}
