{
  "level": 16,
  "title": "전화 통화",
  "titleCn": "打电话",
  "description": "전화 걸기, 받기, 메시지 남기기 등 전화 통화와 관련된 중국어 표현을 배워봅시다.",
  "conversations": [
    { "speaker": "A", "chinese": "喂，你好！请问李明在吗？", "pinyin": "Wèi, nǐ hǎo! Qǐngwèn Lǐ Míng zài ma?", "korean": "여보세요, 안녕하세요! 리밍 있나요?" },
    { "speaker": "B", "chinese": "他在，请等一下，我帮你叫他。", "pinyin": "Tā zài, qǐng děng yīxià, wǒ bāng nǐ jiào tā.", "korean": "있어요, 잠깐만요, 제가 불러줄게요." },
    { "speaker": "A", "chinese": "好的，谢谢你。", "pinyin": "Hǎo de, xièxie nǐ.", "korean": "네, 감사합니다." },
    { "speaker": "B", "chinese": "喂，我是李明，你找我有什么事？", "pinyin": "Wèi, wǒ shì Lǐ Míng, nǐ zhǎo wǒ yǒu shénme shì?", "korean": "여보세요, 저 리밍인데, 무슨 일이에요?" },
    { "speaker": "A", "chinese": "我想问你明天有没有时间一起吃饭。", "pinyin": "Wǒ xiǎng wèn nǐ míngtiān yǒu méiyǒu shíjiān yìqǐ chīfàn.", "korean": "내일 같이 밥 먹을 시간 있는지 물어보려고요." },
    { "speaker": "B", "chinese": "明天下午可以。你打我的手机就行。", "pinyin": "Míngtiān xiàwǔ kěyǐ. Nǐ dǎ wǒ de shǒujī jiù xíng.", "korean": "내일 오후에 가능해요. 제 핸드폰으로 전화하면 돼요." },
    { "speaker": "A", "chinese": "好的，那我明天再给你打电话。", "pinyin": "Hǎo de, nà wǒ míngtiān zài gěi nǐ dǎ diànhuà.", "korean": "좋아요, 그러면 내일 다시 전화할게요." },
    { "speaker": "B", "chinese": "没问题，不过你别打错了，上次你打错了号码。", "pinyin": "Méi wèntí, búguò nǐ bié dǎ cuò le, shàng cì nǐ dǎ cuò le hàomǎ.", "korean": "문제없어요, 근데 잘못 걸지 마세요, 지난번에 번호 잘못 걸었잖아요." }
  ],
  "vocabulary": [
    { "chinese": "打电话", "pinyin": "dǎ diànhuà", "korean": "전화를 걸다" },
    { "chinese": "等一下", "pinyin": "děng yīxià", "korean": "잠깐 기다리다" },
    { "chinese": "手机", "pinyin": "shǒujī", "korean": "핸드폰" },
    { "chinese": "打错了", "pinyin": "dǎ cuò le", "korean": "잘못 걸었다" },
    { "chinese": "号码", "pinyin": "hàomǎ", "korean": "번호" },
    { "chinese": "请问", "pinyin": "qǐngwèn", "korean": "여쭤볼게요 (정중한 질문)" }
  ],
  "quiz": [
    { "type": "cn_to_kr", "question": "打电话", "options": ["편지를 쓰다", "전화를 걸다", "문자를 보내다", "이메일을 보내다"], "answer": 1 },
    { "type": "kr_to_cn", "question": "잠깐 기다리다", "options": ["等一下", "慢一点", "快一点", "走一下"], "answer": 0 },
    { "type": "fill_blank", "question": "喂，___李明在吗？", "options": ["请问", "请坐", "请进", "请说"], "answer": 0 },
    { "type": "cn_to_kr", "question": "打错了", "options": ["잘 걸었다", "끊었다", "잘못 걸었다", "다시 걸었다"], "answer": 2 },
    { "type": "kr_to_cn", "question": "핸드폰", "options": ["电话", "电脑", "手机", "电视"], "answer": 2 }
  ]
}
